taichu_storage/__init__.py
taichu_storage/boto3_client.py
taichu_storage/command.py
taichu_storage/copy.py
taichu_storage/obs_client.py
taichu_storage-1.0.23.dist-info/METADATA
taichu_storage-1.0.23.dist-info/WHEEL
taichu_storage-1.0.23.dist-info/entry_points.txt
taichu_storage-1.0.23.dist-info/top_level.txt
taichu_storage-1.0.23.dist-info/RECORD
