Metadata-Version: 2.1
Name: taichu-storage
Version: 1.0.23
Summary: storage sdks aggregation
Home-page: UNKNOWN
Author: taichu platform team
License: UNKNOWN
Keywords: taichu
Platform: UNKNOWN
Requires-Python: >=3.6.0
Requires-Dist: boto3 (~=1.23.8)
Requires-Dist: botocore (~=1.26.10)
Requires-Dist: setuptools
Requires-Dist: esdk-obs-python (==3.23.12)
Requires-Dist: boto (~=2.49.0)
Requires-Dist: minio (~=7.1.16)
